odoo10_addon_report_hotel_restaurant-10.0.1.0.0.99.dev12-py2.7-nspkg.pth
odoo/addons/report_hotel_restaurant/README.rst
odoo/addons/report_hotel_restaurant/__init__.py
odoo/addons/report_hotel_restaurant/__manifest__.py
odoo/addons/report_hotel_restaurant/Doc/ChangeLog.txt
odoo/addons/report_hotel_restaurant/LICENSE/LICENSE
odoo/addons/report_hotel_restaurant/i18n/es.po
odoo/addons/report_hotel_restaurant/i18n/fr_BE.po
odoo/addons/report_hotel_restaurant/i18n/sv.po
odoo/addons/report_hotel_restaurant/models/__init__.py
odoo/addons/report_hotel_restaurant/models/report_hotel_restaurant.py
odoo/addons/report_hotel_restaurant/security/ir.model.access.csv
odoo/addons/report_hotel_restaurant/static/description/icon.png
odoo/addons/report_hotel_restaurant/static/description/sbrest.png
odoo/addons/report_hotel_restaurant/static/description/serpent.png
odoo/addons/report_hotel_restaurant/views/report_hotel_restaurant_view.xml
odoo10_addon_report_hotel_restaurant-10.0.1.0.0.99.dev12.dist-info/DESCRIPTION.rst
odoo10_addon_report_hotel_restaurant-10.0.1.0.0.99.dev12.dist-info/METADATA
odoo10_addon_report_hotel_restaurant-10.0.1.0.0.99.dev12.dist-info/RECORD
odoo10_addon_report_hotel_restaurant-10.0.1.0.0.99.dev12.dist-info/WHEEL
odoo10_addon_report_hotel_restaurant-10.0.1.0.0.99.dev12.dist-info/metadata.json
odoo10_addon_report_hotel_restaurant-10.0.1.0.0.99.dev12.dist-info/namespace_packages.txt
odoo10_addon_report_hotel_restaurant-10.0.1.0.0.99.dev12.dist-info/top_level.txt
